{
  "main": {
    "id": "c2d2ae632302e35f",
    "type": "split",
    "children": [
      {
        "id": "0fc39f688f4ce1e1",
        "type": "tabs",
        "children": [
          {
            "id": "0bf433099b5f8849",
            "type": "leaf",
            "state": {
              "type": "markdown",
              "state": {
                "file": "Nginx/其它.md",
                "mode": "source",
                "source": false
              },
              "icon": "lucide-file",
              "title": "其它"
            }
          }
        ]
      }
    ],
    "direction": "vertical"
  },
  "left": {
    "id": "d052881ef11894f8",
    "type": "split",
    "children": [
      {
        "id": "24f917333765154f",
        "type": "tabs",
        "children": [
          {
            "id": "8464181af97ad9b5",
            "type": "leaf",
            "state": {
              "type": "file-explorer",
              "state": {
                "sortOrder": "alphabetical"
              },
              "icon": "lucide-folder-closed",
              "title": "文件列表"
            }
          },
          {
            "id": "c9024373c824785f",
            "type": "leaf",
            "state": {
              "type": "search",
              "state": {
                "query": "",
                "matchingCase": false,
                "explainSearch": false,
                "collapseAll": false,
                "extraContext": false,
                "sortOrder": "alphabetical"
              },
              "icon": "lucide-search",
              "title": "搜索"
            }
          },
          {
            "id": "8e54dec708d2b60f",
            "type": "leaf",
            "state": {
              "type": "bookmarks",
              "state": {},
              "icon": "lucide-bookmark",
              "title": "书签"
            }
          }
        ]
      }
    ],
    "direction": "horizontal",
    "width": 300
  },
  "right": {
    "id": "396c7508e5405790",
    "type": "split",
    "children": [
      {
        "id": "43df421d559e6193",
        "type": "tabs",
        "children": [
          {
            "id": "aee4269005a059b7",
            "type": "leaf",
            "state": {
              "type": "backlink",
              "state": {
                "file": "Nginx/动静分离.md",
                "collapseAll": false,
                "extraContext": false,
                "sortOrder": "alphabetical",
                "showSearch": false,
                "searchQuery": "",
                "backlinkCollapsed": false,
                "unlinkedCollapsed": true
              },
              "icon": "links-coming-in",
              "title": "动静分离 的反向链接列表"
            }
          },
          {
            "id": "2b3dd42c09daf0cb",
            "type": "leaf",
            "state": {
              "type": "outgoing-link",
              "state": {
                "file": "Nginx/动静分离.md",
                "linksCollapsed": false,
                "unlinkedCollapsed": true
              },
              "icon": "links-going-out",
              "title": "动静分离 的出链列表"
            }
          },
          {
            "id": "688386c5ba747005",
            "type": "leaf",
            "state": {
              "type": "tag",
              "state": {
                "sortOrder": "frequency",
                "useHierarchy": true
              },
              "icon": "lucide-tags",
              "title": "标签"
            }
          },
          {
            "id": "5fa82b6acd70af36",
            "type": "leaf",
            "state": {
              "type": "outline",
              "state": {
                "file": "Nginx/动静分离.md"
              },
              "icon": "lucide-list",
              "title": "动静分离 的大纲"
            }
          }
        ]
      }
    ],
    "direction": "horizontal",
    "width": 300,
    "collapsed": true
  },
  "left-ribbon": {
    "hiddenItems": {
      "switcher:打开快速切换": false,
      "graph:查看关系图谱": false,
      "canvas:新建白板": false,
      "daily-notes:打开/创建今天的日记": false,
      "templates:插入模板": false,
      "command-palette:打开命令面板": false
    }
  },
  "active": "0bf433099b5f8849",
  "lastOpenFiles": [
    "Nginx/反向代理.md",
    "Nginx/动静分离.md",
    "Nginx/入门.md",
    "Nginx/Hello, world!.md",
    "Nginx/其它.md",
    "Nginx/静态服务器.md",
    "Nginx/负载均衡.md",
    "Nginx/进阶/配置文件.md",
    "Nginx/进阶/限流.md"
  ]
}